Metadata-Version: 1.2
Name: chat-gpt-ppt
Version: 0.2.0
Summary: use ChatGPT to generate PPT automatically
Home-page: https://github.com/williamfzc/chat-gpt-ppt
Author: williamfzc
Author-email: williamfzc@foxmail.com
License: MIT
Platform: UNKNOWN
Classifier: License :: OSI Approved :: MIT License
Classifier: Programming Language :: Python
Classifier: Programming Language :: Python :: 3
Requires-Python: >=3.6
